gaussdb_pool/__init__.py
gaussdb_pool/_acompat.py
gaussdb_pool/_compat.py
gaussdb_pool/_task.py
gaussdb_pool/abc.py
gaussdb_pool/base.py
gaussdb_pool/base_null_pool.py
gaussdb_pool/errors.py
gaussdb_pool/null_pool.py
gaussdb_pool/null_pool_async.py
gaussdb_pool/pool.py
gaussdb_pool/pool_async.py
gaussdb_pool/py.typed
gaussdb_pool/sched.py
gaussdb_pool/sched_async.py
gaussdb_pool/version.py
gaussdb_pool-1.0.4.dist-info/licenses/LICENSE.txt
gaussdb_pool-1.0.4.dist-info/METADATA
gaussdb_pool-1.0.4.dist-info/WHEEL
gaussdb_pool-1.0.4.dist-info/top_level.txt
gaussdb_pool-1.0.4.dist-info/RECORD
